odoo/addons/account_move_line_product/README.rst
odoo/addons/account_move_line_product/__init__.py
odoo/addons/account_move_line_product/__manifest__.py
odoo/addons/account_move_line_product/i18n/account_move_line_product.pot
odoo/addons/account_move_line_product/i18n/ca.po
odoo/addons/account_move_line_product/i18n/cs_CZ.po
odoo/addons/account_move_line_product/i18n/de.po
odoo/addons/account_move_line_product/i18n/el_GR.po
odoo/addons/account_move_line_product/i18n/es.po
odoo/addons/account_move_line_product/i18n/es_ES.po
odoo/addons/account_move_line_product/i18n/eu.po
odoo/addons/account_move_line_product/i18n/fi.po
odoo/addons/account_move_line_product/i18n/fr.po
odoo/addons/account_move_line_product/i18n/fr_CH.po
odoo/addons/account_move_line_product/i18n/fr_FR.po
odoo/addons/account_move_line_product/i18n/gl.po
odoo/addons/account_move_line_product/i18n/hr.po
odoo/addons/account_move_line_product/i18n/hr_HR.po
odoo/addons/account_move_line_product/i18n/it.po
odoo/addons/account_move_line_product/i18n/nl.po
odoo/addons/account_move_line_product/i18n/nl_NL.po
odoo/addons/account_move_line_product/i18n/pt.po
odoo/addons/account_move_line_product/i18n/pt_BR.po
odoo/addons/account_move_line_product/i18n/ro.po
odoo/addons/account_move_line_product/i18n/ru.po
odoo/addons/account_move_line_product/i18n/sl.po
odoo/addons/account_move_line_product/i18n/tr.po
odoo/addons/account_move_line_product/i18n/tr_TR.po
odoo/addons/account_move_line_product/i18n/vi_VN.po
odoo/addons/account_move_line_product/i18n/zh_CN.po
odoo/addons/account_move_line_product/readme/CONTRIBUTORS.rst
odoo/addons/account_move_line_product/readme/DESCRIPTION.rst
odoo/addons/account_move_line_product/static/description/icon.png
odoo/addons/account_move_line_product/static/description/index.html
odoo/addons/account_move_line_product/views/account_move_line_view.xml
odoo13_addon_account_move_line_product-13.0.1.0.1.dev7.dist-info/METADATA
odoo13_addon_account_move_line_product-13.0.1.0.1.dev7.dist-info/WHEEL
odoo13_addon_account_move_line_product-13.0.1.0.1.dev7.dist-info/top_level.txt
odoo13_addon_account_move_line_product-13.0.1.0.1.dev7.dist-info/RECORD
